sugcommand/__init__.py
sugcommand/cli.py
sugcommand/core/__init__.py
sugcommand/core/command_scanner.py
sugcommand/core/config_manager.py
sugcommand/core/history_analyzer.py
sugcommand/core/suggestion_engine.py
sugcommand/integrations/__init__.py
sugcommand/integrations/auto_suggest.py
sugcommand/integrations/bash_integration.py
sugcommand/integrations/fish_integration.py
sugcommand/integrations/realtime_daemon.py
sugcommand/integrations/zsh_integration.py
sugcommand/shell/auto_suggest_daemon.py
sugcommand/utils/__init__.py
sugcommand/utils/display.py
sugcommand/utils/performance.py
sugcommand-0.3.0.dist-info/licenses/LICENSE
sugcommand-0.3.0.dist-info/METADATA
sugcommand-0.3.0.dist-info/WHEEL
sugcommand-0.3.0.dist-info/entry_points.txt
sugcommand-0.3.0.dist-info/top_level.txt
sugcommand-0.3.0.dist-info/RECORD
