Metadata-Version: 2.4
Name: sugcommand
Version: 0.3.0
Summary: Intelligent terminal command suggestion tool with real-time shell integration, customizable key bindings, and smart command history analysis
Author: imnahn
License: MIT
Project-URL: Homepage, https://github.com/yourusername/sugcommand
Project-URL: Repository, https://github.com/yourusername/sugcommand
Project-URL: Documentation, https://github.com/yourusername/sugcommand#readme
Project-URL: Changelog, https://github.com/yourusername/sugcommand/blob/main/CHANGELOG.md
Keywords: terminal,command,suggestion,autocomplete,cli,bash,zsh,fish,shell,integration,key-bindings,command-history,real-time-suggestions
Classifier: Development Status :: 4 - Beta
Classifier: Intended Audience :: Developers
Classifier: Intended Audience :: System Administrators
Classifier: License :: OSI Approved :: MIT License
Classifier: Operating System :: POSIX :: Linux
Classifier: Operating System :: Unix
Classifier: Operating System :: MacOS
Classifier: Programming Language :: Python :: 3
Classifier: Programming Language :: Python :: 3.8
Classifier: Programming Language :: Python :: 3.9
Classifier: Programming Language :: Python :: 3.10
Classifier: Programming Language :: Python :: 3.11
Classifier: Programming Language :: Python :: 3.12
Classifier: Topic :: System :: Shells
Classifier: Topic :: System :: System Shells
Classifier: Topic :: Terminals
Classifier: Topic :: Utilities
Requires-Python: >=3.8
License-File: LICENSE
Requires-Dist: click>=8.0.0
Requires-Dist: colorama>=0.4.0
Requires-Dist: prompt-toolkit>=3.0.0
Provides-Extra: dev
Requires-Dist: pytest>=6.0; extra == "dev"
Requires-Dist: pytest-cov>=2.10; extra == "dev"
Requires-Dist: black>=21.0; extra == "dev"
Requires-Dist: isort>=5.0; extra == "dev"
Requires-Dist: flake8>=3.8; extra == "dev"
Requires-Dist: mypy>=0.900; extra == "dev"
Provides-Extra: daemon
Requires-Dist: psutil>=5.8.0; extra == "daemon"
Provides-Extra: all
Requires-Dist: psutil>=5.8.0; extra == "all"
Dynamic: license-file
